<?xml version='1.0' encoding='UTF-8'?>
<types:mule xmlns:types="http://www.mulesoft.org/schema/mule/types">
  <types:catalog>
    <types:type name="all" format="json">
      <types:shape format="weave" example="examples/all.json"><![CDATA[%dw 2.0

type all = Array<{|  complaintID: String,   description: String,   status: String,   customerID: String,   orderNumber: String,   productCode: String|}> {"example": "[{\\\"complaintID\\\":\\\"CP101\\\",\\\"description\\\":\\\"Wrong Item Received\\\",\\\"status\\\":\\\"Opened\\\",\\\"customerID\\\":\\\"C001\\\",\\\"orderNumber\\\":\\\"O101\\\",\\\"productCode\\\":\\\"P1001\\\"},{\\\"complaintID\\\":\\\"CP102\\\",\\\"description\\\":\\\"Wrong Item Received\\\",\\\"status\\\":\\\"Opened\\\",\\\"customerID\\\":\\\"C002\\\",\\\"orderNumber\\\":\\\"O101\\\",\\\"productCode\\\":\\\"P1001\\\"}]"}

]]></types:shape>
    </types:type>
    <types:type name="single" format="json">
      <types:shape format="weave" example="examples/singlecomplaint.json"><![CDATA[%dw 2.0

type single = {|
  complaintID: String, 
  description: String, 
  status: String, 
  customerID: String, 
  orderNumber: String, 
  productCode: String
|} {"example": "{\\\"complaintID\\\":\\\"CP101\\\",\\\"description\\\":\\\"Wrong Item Received\\\",\\\"status\\\":\\\"Opened\\\",\\\"customerID\\\":\\\"C001\\\",\\\"orderNumber\\\":\\\"O101\\\",\\\"productCode\\\":\\\"P100\\\"}"}

]]></types:shape>
    </types:type>
  </types:catalog>
  <types:enrichment select="#d8576ad5-2339-4574-9fc8-6c500d162abe">
    <types:processor-declaration>
      <types:output-event>
        <types:message>
          <types:payload type="all"/>
        </types:message>
      </types:output-event>
    </types:processor-declaration>
  </types:enrichment>
  <types:enrichment select="#a4c307a4-20f6-4059-9700-ada35fc83657">
    <types:processor-declaration>
      <types:output-event>
        <types:message>
          <types:payload type="single"/>
        </types:message>
      </types:output-event>
    </types:processor-declaration>
  </types:enrichment>
</types:mule>